qrn/__init__.py
qrn/code_generator.py
qrn/components.py
qrn/converters.py
qrn/epy.py
qrn/expander.py
qrn/paml.py
qrn/paml_line_parser.py
qrn/paml_node.py
qrn/pipeline.py
qrn/qrn.py
qrn/rss.py
qrn/utils.py
qrn-0.10.0.dist-info/METADATA
qrn-0.10.0.dist-info/WHEEL
qrn-0.10.0.dist-info/licenses/LICENSE
qrn-0.10.0.dist-info/RECORD
