Metadata-Version: 2.1
Name: qrn
Version: 0.10.0
Summary: A simple static site generator
Project-URL: Homepage, https://github.com/russolsen/qrn
Project-URL: Bug Tracker, https://github.com/russolsen/qrn/issues
Author-email: Russ Olsen <russ@russolsen.com>
License: MIT License
License-File: LICENSE
Classifier: License :: OSI Approved :: MIT License
Classifier: Operating System :: OS Independent
Classifier: Programming Language :: Python :: 3
Requires-Python: >=3.7
Requires-Dist: pyyaml>=6.0
